py_observatory/__init__.py
py_observatory/config.py
py_observatory/observatory.py
py_observatory/collectors/__init__.py
py_observatory/collectors/cronjob.py
py_observatory/collectors/inbound.py
py_observatory/collectors/outbound.py
py_observatory/exceptions/__init__.py
py_observatory/exceptions/handler.py
py_observatory/exporters/__init__.py
py_observatory/exporters/base.py
py_observatory/exporters/prometheus.py
py_observatory/http_client/__init__.py
py_observatory/http_client/httpx_client.py
py_observatory/middleware/__init__.py
py_observatory/middleware/inbound.py
py_observatory/routes/__init__.py
py_observatory/routes/metrics.py
py_observatory/storage/__init__.py
py_observatory/storage/base.py
py_observatory/storage/file.py
py_observatory/storage/memory.py
py_observatory/storage/redis.py
py_observatory-0.1.0.dist-info/METADATA
py_observatory-0.1.0.dist-info/WHEEL
py_observatory-0.1.0.dist-info/licenses/LICENSE
py_observatory-0.1.0.dist-info/RECORD
