Metadata-Version: 2.4
Name: py-observatory
Version: 0.1.0
Summary: FastAPI Prometheus monitoring package inspired by Laravel Observatory
Project-URL: Homepage, https://github.com/junixlabs/py-observatory
Project-URL: Documentation, https://py-observatory.readthedocs.io
Project-URL: Repository, https://github.com/junixlabs/py-observatory
Author-email: JunixLabs <contact@junixlabs.com>
License: MIT
License-File: LICENSE
Keywords: apm,fastapi,metrics,monitoring,observability,prometheus
Classifier: Development Status :: 4 - Beta
Classifier: Framework :: FastAPI
Classifier: Intended Audience :: Developers
Classifier: License :: OSI Approved :: MIT License
Classifier: Programming Language :: Python :: 3
Classifier: Programming Language :: Python :: 3.9
Classifier: Programming Language :: Python :: 3.10
Classifier: Programming Language :: Python :: 3.11
Classifier: Programming Language :: Python :: 3.12
Classifier: Topic :: System :: Monitoring
Requires-Python: >=3.9
Requires-Dist: fastapi>=0.100.0
Requires-Dist: httpx>=0.24.0
Requires-Dist: starlette>=0.27.0
Provides-Extra: all
Requires-Dist: aiofiles>=23.0.0; extra == 'all'
Requires-Dist: redis>=4.5.0; extra == 'all'
Provides-Extra: dev
Requires-Dist: fakeredis>=2.20.0; extra == 'dev'
Requires-Dist: mypy>=1.0.0; extra == 'dev'
Requires-Dist: pytest-asyncio>=0.21.0; extra == 'dev'
Requires-Dist: pytest-cov>=4.0.0; extra == 'dev'
Requires-Dist: pytest>=7.0.0; extra == 'dev'
Requires-Dist: ruff>=0.1.0; extra == 'dev'
Provides-Extra: file
Requires-Dist: aiofiles>=23.0.0; extra == 'file'
Provides-Extra: redis
Requires-Dist: redis>=4.5.0; extra == 'redis'
